top30/__init__.py
top30/chart.py
top30/clip_list.py
top30/handlers.py
top30/icon.ico
top30/main_window.ui
top30/settings.py
top30/top_30_creator.py
top30-2.0.0.dist-info/LICENCE.md
top30-2.0.0.dist-info/METADATA
top30-2.0.0.dist-info/WHEEL
top30-2.0.0.dist-info/entry_points.txt
top30-2.0.0.dist-info/top_level.txt
top30-2.0.0.dist-info/RECORD
