Metadata-Version: 2.1
Name: top30
Version: 2.0.0
Summary: Creates rundowns from Top 30 charts
Home-page: https://gitlab.com/paddatrapper/top30
Author: Kyle Robbertze
Author-email: krobbertze@gmail.com
License: GPL-3
Keywords: radio audio rundown
Platform: UNKNOWN
Classifier: Development Status :: 5 - Production/Stable
Classifier: Intended Audience :: Other Audience
Classifier: Topic :: Multimedia :: Sound/Audio
Classifier: License :: OSI Approved :: GNU General Public License v3 (GPLv3)
Classifier: Programming Language :: Python :: 3
Classifier: Programming Language :: Python :: 3.4
Classifier: Programming Language :: Python :: 3.5
Classifier: Programming Language :: Python :: 3.6
Requires-Dist: mutagen
Requires-Dist: pydub
Requires-Dist: youtube-dl
Requires-Dist: PyQt5
